pylife_api/__init__.py
pylife_api/client.py
pylife_api/models/__init__.py
pylife_api/models/house.py
pylife_api/models/organization.py
pylife_api/models/player.py
pylife_api-0.1.3.dist-info/LICENSE
pylife_api-0.1.3.dist-info/WHEEL
pylife_api-0.1.3.dist-info/METADATA
pylife_api-0.1.3.dist-info/RECORD
