Metadata-Version: 2.1
Name: pylife-api
Version: 0.1.3
Summary: Python API for Play Your Life v2 user panel.
Keywords: pylife,mta,api
Author-email: David Sn <divad.nnamtdeis@gmail.com>
Requires-Python: >=3.7
Classifier: Development Status :: 4 - Beta
Classifier: Intended Audience :: Developers
Classifier: License :: OSI Approved :: MIT License
Classifier: Programming Language :: Python :: 3.7
Classifier: Programming Language :: Python :: 3.8
Classifier: Programming Language :: Python :: 3.9
Classifier: Programming Language :: Python :: 3.10
Classifier: Programming Language :: Python :: 3.11
Classifier: Programming Language :: Python :: 3.12
Requires-Dist: aiohttp >=3.10.5,<4
Requires-Dist: pydantic >=2.9.1,<3
Requires-Dist: python-rapidjson >=1.20,<2 ; extra == "rapidjson"
Project-URL: Home, https://github.com/mapapylife/python-pylife
Provides-Extra: rapidjson
